apple_notes_mcp/__init__.py
apple_notes_mcp/notes_database.py
apple_notes_mcp/server.py
apple_notes_mcp/proto/notestore.proto
apple_notes_mcp/proto/notestore_pb2.py
apple_notes_mcp-0.1.1.dist-info/METADATA
apple_notes_mcp-0.1.1.dist-info/WHEEL
apple_notes_mcp-0.1.1.dist-info/entry_points.txt
apple_notes_mcp-0.1.1.dist-info/licenses/LICENSE
apple_notes_mcp-0.1.1.dist-info/RECORD
