Metadata-Version: 2.3
Name: apple-notes-mcp
Version: 0.1.1
Summary: Read local Apple Notes sqlite database and provide it as a context protocol server for Claude Desktop.
Project-URL: homepage, https://sirmews.github.io/apple-notes-mcp/
Author-email: Navishkar Rao <sirmews@gmail.com>
Classifier: License :: OSI Approved :: MIT License
Classifier: Operating System :: MacOS
Classifier: Programming Language :: Python :: 3
Requires-Python: >=3.12
Requires-Dist: httpx>=0.28.0
Requires-Dist: mcp>=1.0.0
Requires-Dist: protobuf>=5.29.0
Requires-Dist: python-dotenv>=1.0.1
